sim4rec/__init__.py
sim4rec/modules/__init__.py
sim4rec/modules/embeddings.py
sim4rec/modules/evaluation.py
sim4rec/modules/generator.py
sim4rec/modules/selectors.py
sim4rec/modules/simulator.py
sim4rec/params/__init__.py
sim4rec/params/params.py
sim4rec/response/__init__.py
sim4rec/response/response.py
sim4rec/utils/__init__.py
sim4rec/utils/convert.py
sim4rec/utils/uce.py
sim4rec-0.0.2.dist-info/LICENSE
sim4rec-0.0.2.dist-info/METADATA
sim4rec-0.0.2.dist-info/WHEEL
sim4rec-0.0.2.dist-info/RECORD
