Metadata-Version: 2.1
Name: sim4rec
Version: 0.0.2
Summary: Simulator for recommendation algorithms
Home-page: https://github.com/sb-ai-lab/Sim4Rec
Author: Alexey Vasilev
Requires-Python: >=3.8,<3.10
Classifier: Programming Language :: Python :: 3
Classifier: Programming Language :: Python :: 3.8
Classifier: Programming Language :: Python :: 3.9
Requires-Dist: numpy (>=1.20.0)
Requires-Dist: pandas
Requires-Dist: pyspark (>=3.0)
Requires-Dist: replay-rec (>=0.10.0)
Requires-Dist: scipy
Requires-Dist: sdv (==0.15.0)
Requires-Dist: torch
Project-URL: Repository, https://github.com/sb-ai-lab/Sim4Rec
